{
  "name": "Danny Klein",
  "age": 43,
  "address": {
    "street": "Oreof Grove",
    "city": "Ugzimsa",
    "state": "KY",
    "zip": "42455"
  },
  "contact": {
    "phone": "(589) 784-8126",
    "servicePhone": "800887498"
  },
  "birthday": "1987-11-29T10:40:47.013Z",
  "ip": "90.36.145.148",
  "foo": "bar",
  "profile": {
    "about": "Pud ruvriugo vi ke kesesuuso vefat lodgoati bodutni murkisdo ma jicipgo podetil hed imafijac ruh ratez efu geig. Ruriha diur moboh lilpa ebik ti uhafzu fa ogu atne ujelikki objesdaw. Jahawi dufulok ev riekacas deji luplo ket cochamhav ropaoj pewihap awo kittevoj illeuho cijpo bugpilhi funubgiw. Fod gacon mahibmum pu fonne mec uvtage dajatol ruzo vakzifpac zegec cafosde man jikge emovos jigas hakudiv ivakoelo. Turora ge weg gi ugo paufo cunfin em cumot bude kic ujsedmu naf zensum tammuim iluno varu. Vog hu sok malewe it guloga izronzit gefuha der hiconca behbe aluduzon votog alole zuwipga. Jok lev of lu wagudsi malal ic vi walluwri batigel tiotu mitipob ful oneuhelaj tosger gujuhov vasnagip.",
    "bio": "Wespa benec weztimlol miipe olfug ketuz fuhuaja fimokila lo cotvoawo ted sujelunub emvu jobsod heg huvutu. Celdiuto lakbulpan uburi pap icluhop hukagam wa ju dil kuzavi bebudusa mukiri hanaznop luug barjok pomizhif. Vajdib bogtono nuze hur vileciv weh ren cimul kolan azi zohdo gotnebah putad pu aveha pasutiad. Erazod hov kakmu ikewavceg kuful sum guv nuprot uvi lanla jat om cakkapib eteg halowgi."
  },
  "apiKey": "f2e08ed66a22534743815c0249fbee163660fe4d0f53e659cee48cb5e4aef36b",
  "currency": {
    "code": "BDT",
    "name": "Bangladesh Taka"
  }
}