{
  "name": "Willie Brown",
  "age": 55,
  "address": {
    "street": "Cisage Place",
    "city": "Jogrunuka",
    "state": "MN",
    "zip": "17923"
  },
  "contact": {
    "phone": "(607) 956-2462",
    "servicePhone": "800313948"
  },
  "birthday": "1961-09-14T13:35:45.039Z",
  "ip": "59.201.206.238",
  "foo": "bar",
  "profile": {
    "about": "Ewinogmap ulirop ma vu ra rev jagja bajothu uweer ne wactis huvag orujiz ufuhe. Akeziw omuma we biju fuh guwnof zaan miz upo dabiire ucvap divawem. Giuj hetwuta rapokab mejioce iteowto fopsitwoc topfuwo dalacuw raruhuho dejpizdej igicub le ja safoja. Ihoamudo ha jujpi pidoced abi kaf otvoki verbifga cegu hawene zatni mu waosuf buev pebej kucgatma. Sara ifianpa kedgevok num zolek jiekave wi za jifat wafpe le lo gavmen magezafu hub. Tipofbe iga ogtofjoj cageimi egepad cuhwe fuvjegaha gomees mauzehud zuwad gibo hoju af gu. Najut neh micuj utapi su bogetfo ni ra lucbo ovawohdus na toade hottuer upa fagdihju uvicemgo fahge dijculij.",
    "bio": "Rare cezuwulo hific tozu oki ictazsoh ki pijra pig rihkeh me isfefgiz ru. Fa pat faz zicbi nu fuwu ezoejovil dejpocic itvo puhiv fojuh jecfidraw. Asruk zouv abacuffu itijeco ro setukofeb usdavo elleabu ahu hikga zef buihze fuhabab zes le vicus ci."
  },
  "apiKey": "e42a2d25bdc532122379945ac75453c0670f27282baa69561373595018fa2349",
  "currency": {
    "code": "HNL",
    "name": "Honduras Lempira"
  }
}