{
  "name": "Rose Bailey",
  "age": 26,
  "address": {
    "street": "Sucor Terrace",
    "city": "Nukatuf",
    "state": "AZ",
    "zip": "77012"
  },
  "contact": {
    "phone": "(703) 212-3508",
    "servicePhone": "800783447"
  },
  "birthday": "1997-10-17T21:35:10.634Z",
  "ip": "122.70.50.46",
  "foo": "bar",
  "profile": {
    "about": "Zatorwo hec nukgob zuw vozod te cehni wero mo loaller ektopjet sovkecdu ujge cawtal za. Duvipor uh cubmu afowegu wamoh bonkim nuh wesotkib lovopos vi runaw soz ecvokof kigiwjig sekwof japogo je. Laj jozuef poj lubu ben cassanu imen rocetkom akfaz duinine revgawi rajagubed bifavil witim poosubi.",
    "bio": "Masonito iwauho hicumub serihho ko raarepo wo vuvewujij takzu ewzedlur lez buszoid ip. Kingarizu pun tucuhew weg mefzilup tipme rudgibze gema ge ojdus reweknat javvurec ivsotaj za ka. Niesdu so zeladi jiw kak gojvewjoz ci beztese agediva epcu im fu je guegutut colsi ubafibunu ge."
  },
  "apiKey": "1032322b2f954582701cc1bffb68deca845d1c7f6367434e672464fd9a5a47b1",
  "currency": {
    "code": "MKD",
    "name": "Macedonia Denar"
  }
}